melobot/__init__.py
melobot/__main__.py
melobot/_hook.py
melobot/_imp.py
melobot/_lazy.py
melobot/_meta.py
melobot/_render.py
melobot/_run.py
melobot/ctx.py
melobot/di.py
melobot/exceptions.py
melobot/mixin.py
melobot/mp.py
melobot/py.typed
melobot/_cli/dev.py
melobot/_cli/pinit.py
melobot/_cli/run.py
melobot/adapter/__init__.py
melobot/adapter/base.py
melobot/adapter/content.py
melobot/adapter/generic.py
melobot/adapter/model.py
melobot/bot/__init__.py
melobot/bot/base.py
melobot/bot/dispatch.py
melobot/handle/__init__.py
melobot/handle/base.py
melobot/handle/graph.py
melobot/handle/register.py
melobot/io/__init__.py
melobot/io/base.py
melobot/log/__init__.py
melobot/log/base.py
melobot/log/handler.py
melobot/log/patch.py
melobot/log/reflect.py
melobot/log/report.py
melobot/plugin/__init__.py
melobot/plugin/__init__.template.py
melobot/plugin/base.py
melobot/plugin/ipc.py
melobot/plugin/load.py
melobot/protocols/__init__.py
melobot/protocols/base.py
melobot/protocols/onebot/__init__.py
melobot/protocols/onebot/v11/__init__.py
melobot/protocols/onebot/v11/const.py
melobot/protocols/onebot/v11/handle.py
melobot/protocols/onebot/v11/adapter/__init__.py
melobot/protocols/onebot/v11/adapter/action.py
melobot/protocols/onebot/v11/adapter/base.py
melobot/protocols/onebot/v11/adapter/echo.py
melobot/protocols/onebot/v11/adapter/event.py
melobot/protocols/onebot/v11/adapter/segment.py
melobot/protocols/onebot/v11/io/__init__.py
melobot/protocols/onebot/v11/io/base.py
melobot/protocols/onebot/v11/io/duplex_http.py
melobot/protocols/onebot/v11/io/forward.py
melobot/protocols/onebot/v11/io/packet.py
melobot/protocols/onebot/v11/io/reverse.py
melobot/protocols/onebot/v11/utils/__init__.py
melobot/protocols/onebot/v11/utils/check.py
melobot/session/__init__.py
melobot/session/base.py
melobot/session/option.py
melobot/typ/__init__.py
melobot/typ/_enum.py
melobot/typ/base.py
melobot/typ/cls.py
melobot/utils/__init__.py
melobot/utils/atool.py
melobot/utils/base.py
melobot-3.2.2.dist-info/METADATA
melobot-3.2.2.dist-info/WHEEL
melobot-3.2.2.dist-info/licenses/LICENSE-BSD
melobot-3.2.2.dist-info/licenses/LICENSE-CC
melobot-3.2.2.dist-info/licenses/THIRD-PARTY-NOTICES.md
melobot-3.2.2.dist-info/RECORD
