Metadata-Version: 2.4
Name: melobot
Version: 3.2.2
Summary: A bot framework with much high level features.
Project-URL: Homepage, https://github.com/Meloland/melobot
Project-URL: Documentation, https://docs.melobot.org
Project-URL: Repository, https://github.com/Meloland/melobot.git
Project-URL: Issues, https://github.com/Meloland/melobot/issues
Author-email: aicorein <aicorein@meloland.org>
Maintainer-email: aicorein <aicorein@meloland.org>
License-Expression: BSD-3-Clause
License-File: LICENSE-BSD
License-File: LICENSE-CC
License-File: THIRD-PARTY-NOTICES.md
Keywords: asyncio,bot framework,concurrency,coroutine,melobot
Classifier: Development Status :: 5 - Production/Stable
Classifier: Environment :: Console
Classifier: Intended Audience :: Developers
Classifier: License :: OSI Approved :: BSD License
Classifier: Operating System :: OS Independent
Classifier: Programming Language :: Python :: 3
Classifier: Programming Language :: Python :: 3.10
Classifier: Programming Language :: Python :: 3.11
Classifier: Programming Language :: Python :: 3.12
Classifier: Programming Language :: Python :: 3.13
Classifier: Programming Language :: Python :: 3.14
Classifier: Programming Language :: Python :: Implementation :: CPython
Classifier: Topic :: Software Development :: Libraries :: Python Modules
Classifier: Typing :: Typed
Requires-Python: >=3.10
Requires-Dist: beartype>=0.18.5
Requires-Dist: better-exceptions==0.3.3
Requires-Dist: colorlog<7,>=6.8.2
Requires-Dist: rich<14,>=13.7.1
Requires-Dist: typing-extensions>=4.10.0
Provides-Extra: cli
Requires-Dist: watchdog<7,>=6.0.0; extra == 'cli'
Provides-Extra: onebot
Requires-Dist: aiohttp<4,>=3.10.10; extra == 'onebot'
Requires-Dist: pydantic<3,>=2.9.2; extra == 'onebot'
Requires-Dist: websockets<15,>=14.1; extra == 'onebot'
